variant/__init__.py
variant/cli.py
variant/coordinate.py
variant/effect.py
variant/effect_ordering.py
variant/motif.py
variant/seqpy.c
variant/seqpy.cpython-312-i386-linux-gnu.so
variant/utils.py
variant-0.0.98.dist-info/METADATA
variant-0.0.98.dist-info/WHEEL
variant-0.0.98.dist-info/entry_points.txt
variant-0.0.98.dist-info/top_level.txt
variant-0.0.98.dist-info/RECORD
variant-0.0.98.dist-info/licenses/LICENSE
