Metadata-Version: 2.4
Name: variant
Version: 0.0.98
Summary: annotate variant
Author-email: Chang Ye <yech1990@gmail.com>
License-Expression: MIT
Project-URL: Repository, https://github.com/yech1990/variant
Keywords: bioinformatics,variant,mutation,RNA modification
Requires-Python: >=3.11
License-File: LICENSE
Requires-Dist: rich-click>=1.8.2
Requires-Dist: xopen>=2.0.2
Requires-Dist: pysam>=0.22.0
Requires-Dist: pyensembl>=2.2.4
Requires-Dist: biopython>=1.85
Requires-Dist: pyarrow>=19.0
Requires-Dist: varcode
Dynamic: license-file
